openedx_learning/__init__.py
openedx_learning/py.typed
openedx_learning/api/__init__.py
openedx_learning/api/authoring.py
openedx_learning/api/authoring_models.py
openedx_learning/apps/__init__.py
openedx_learning/apps/authoring/__init__.py
openedx_learning/apps/authoring/backup_restore/__init__.py
openedx_learning/apps/authoring/backup_restore/admin.py
openedx_learning/apps/authoring/backup_restore/api.py
openedx_learning/apps/authoring/backup_restore/apps.py
openedx_learning/apps/authoring/backup_restore/models.py
openedx_learning/apps/authoring/backup_restore/serializers.py
openedx_learning/apps/authoring/backup_restore/toml.py
openedx_learning/apps/authoring/backup_restore/zipper.py
openedx_learning/apps/authoring/backup_restore/management/__init__.py
openedx_learning/apps/authoring/backup_restore/management/commands/__init__.py
openedx_learning/apps/authoring/backup_restore/management/commands/lp_dump.py
openedx_learning/apps/authoring/backup_restore/management/commands/lp_load.py
openedx_learning/apps/authoring/backup_restore/migrations/__init__.py
openedx_learning/apps/authoring/collections/__init__.py
openedx_learning/apps/authoring/collections/admin.py
openedx_learning/apps/authoring/collections/api.py
openedx_learning/apps/authoring/collections/apps.py
openedx_learning/apps/authoring/collections/models.py
openedx_learning/apps/authoring/collections/migrations/0001_initial.py
openedx_learning/apps/authoring/collections/migrations/0002_remove_collection_name_collection_created_by_and_more.py
openedx_learning/apps/authoring/collections/migrations/0003_collection_entities.py
openedx_learning/apps/authoring/collections/migrations/0004_collection_key.py
openedx_learning/apps/authoring/collections/migrations/0005_alter_collection_options_alter_collection_enabled.py
openedx_learning/apps/authoring/collections/migrations/__init__.py
openedx_learning/apps/authoring/components/__init__.py
openedx_learning/apps/authoring/components/admin.py
openedx_learning-0.30.2.dist-info/licenses/LICENSE.txt
openedx_learning-0.30.2.dist-info/METADATA
openedx_learning-0.30.2.dist-info/WHEEL
openedx_learning-0.30.2.dist-info/top_level.txt
openedx_learning-0.30.2.dist-info/RECORD
