Metadata-Version: 2.4
Name: openedx-learning
Version: 0.30.2
Summary: Open edX Learning Core and Tagging.
Home-page: https://github.com/openedx/openedx-learning
Author: David Ormsbee
Author-email: dave@tcril.org
License: AGPL 3.0
Keywords: Python edx
Classifier: Development Status :: 3 - Alpha
Classifier: Framework :: Django
Classifier: Framework :: Django :: 4.2
Classifier: Framework :: Django :: 5.2
Classifier: Intended Audience :: Developers
Classifier: License :: OSI Approved :: GNU Affero General Public License v3 or later (AGPLv3+)
Classifier: Natural Language :: English
Classifier: Programming Language :: Python :: 3
Classifier: Programming Language :: Python :: 3.11
Classifier: Programming Language :: Python :: 3.12
Requires-Python: >=3.11
License-File: LICENSE.txt
Requires-Dist: attrs
Requires-Dist: djangorestframework<4.0
Requires-Dist: edx-drf-extensions
Requires-Dist: tomlkit
Requires-Dist: celery
Requires-Dist: Django
Requires-Dist: rules<4.0
Dynamic: author
Dynamic: author-email
Dynamic: classifier
Dynamic: description
Dynamic: home-page
Dynamic: keywords
Dynamic: license
Dynamic: license-file
Dynamic: requires-dist
Dynamic: requires-python
Dynamic: summary
